{
    "title": "MQF",
    "sections": [
        {
            "name": "MORE AL",
            "questions": [
                {
                    "num": 1,
                    "question": "How much wood cood a wood chuk chuk if a wood chuck cood chuck wood?",
                    "ref": "NAT4YOU PI 1.1",
                    "correct": [
                        3, 5
                    ],
                    "choices": [
                        "Alot, cuz he's a wizard",
                        ">5",
                        "Failed MC",
                        "More if he wasnt lonely",
                        "Sponson dump only",
                        "None, cuz he's a wizard, a wizard of loneliness"
                    ]
                },
                {
                    "num": 2,
                    "question": "When trying to access the second element of a zero based array, what do I use?",
                    "ref": "ARRAY - 1 V 22-22-22-2",
                    "correct": [1],
                    "choices": ["0", "1", "2", "3"]
                },
                {
                    "num": 3,
                    "question": "I answered my _____",
                    "ref": "AIRMANS MANUAL",
                    "correct": [2],
                    "choices": ["nations call", "door", "tests question", "my phone"]
                },
                {
                    "num": 4,
                    "question": "How many oge's is just too many oge's?",
                    "ref": "1V-22(C)B-1, Pg: 2-74",
                    "correct": [3],
                    "choices": ["5", "10", "20", "what a ridiculous question"]
                }, {
                    "num": 5,
                    "question": "How many lifties exist in continental United States airspace during the daytime?",
                    "ref": "1V-22(C)B-1, Pg: 2-74",
                    "correct": [4],
                    "choices": [
                        "√(-250)",
                        "The Ratio of Leprechauns to Unicorns",
                        "Sometimes",
                        "The Inverse Ratio of Sinkies at Night in The Southern Hemisphere",
                        "8"
                    ]
                }, {
                    "num": 6,
                    "question": "If its 30 deg C out, and EP of the day is inadvertant icing, should you do something more relatable to your flight?",
                    "ref": "1V-22(C)B-1, Pg: 2-74",
                    "correct": [3],
                    "choices": [
                        "Yes",
                        "Refer to flight lead",
                        "Absolutely not",
                        "No you shouldnt because when do you think you're going to get inadvertant icing, when you're planning on it?",
                        "Maybe"
                    ]
                }
            ]
        }
    ]
}
